setup.py
AbiHandler.egg-info/PKG-INFO
AbiHandler.egg-info/SOURCES.txt
AbiHandler.egg-info/dependency_links.txt
AbiHandler.egg-info/requires.txt
AbiHandler.egg-info/top_level.txt
AbiHandler.egg-info/zip-safe
abi_handler/__init__.py
abi_handler/abi_handler.py