Metadata-Version: 1.1
Name: AbiHandler
Version: 0.0.1
Summary: Handler for abi
Home-page: https://github.com/LeagueOfBlockchain/AbiHandler
Author: tinghsuwan
Author-email: wanth1997@gmail.com
License: MIT
Platform: UNKNOWN
Classifier: Programming Language :: Python :: 3
Classifier: License :: OSI Approved :: MIT License
Classifier: Operating System :: OS Independent
